README.md
setup.py
log/__init__.py
log/log_module.py
lsaf_log_module.egg-info/PKG-INFO
lsaf_log_module.egg-info/SOURCES.txt
lsaf_log_module.egg-info/dependency_links.txt
lsaf_log_module.egg-info/requires.txt
lsaf_log_module.egg-info/top_level.txt